SWFUtils/__init__.py
SWFUtils/reader.py
SWFUtils/workload.py
SWFUtils/writer.py
tests/__init__.py
tests/test_reader.py
tests/test_workload.py
tests/test_writer.py
SWFUtils-0.1.0.dist-info/LICENSE
SWFUtils-0.1.0.dist-info/METADATA
SWFUtils-0.1.0.dist-info/WHEEL
SWFUtils-0.1.0.dist-info/top_level.txt
SWFUtils-0.1.0.dist-info/RECORD
